oktactl/__init__.py
oktactl/okta.py
oktactl/utils.py
oktactl-0.0.2.dist-info/LICENCE.txt
oktactl-0.0.2.dist-info/METADATA
oktactl-0.0.2.dist-info/WHEEL
oktactl-0.0.2.dist-info/entry_points.txt
oktactl-0.0.2.dist-info/top_level.txt
oktactl-0.0.2.dist-info/zip-safe
oktactl-0.0.2.dist-info/RECORD
